[
    {
        "data": "26/04/2026",
        "moeda": "BITCOIN",
        "previsao": 78748.41,
        "confianca_min": 72637.71,
        "confianca_max": 84742.8,
        "preco_real": null,
        "erro": null,
        "acerto": null
    },
    {
        "data": "26/04/2026",
        "moeda": "ETHEREUM",
        "previsao": 2364.27,
        "confianca_min": 2028.14,
        "confianca_max": 2720.42,
        "preco_real": null,
        "erro": null,
        "acerto": null
    },
    {
        "data": "26/04/2026",
        "moeda": "SOLANA",
        "previsao": 87.01,
        "confianca_min": 71.06,
        "confianca_max": 103.01,
        "preco_real": null,
        "erro": null,
        "acerto": null
    },
    {
        "data": "26/04/2026",
        "moeda": "CARDANO",
        "previsao": 0.25,
        "confianca_min": 0.19,
        "confianca_max": 0.32,
        "preco_real": null,
        "erro": null,
        "acerto": null
    }
]